qcml/__init__.py
qcml/bench/__init__.py
qcml/bench/checkpoint.py
qcml/bench/grid_search.py
qcml/bench/model_evaluator.py
qcml/bench/parameter_grid.py
qcml/bench/grids/__init__.py
qcml/bench/grids/kernel_grid.py
qcml/bench/grids/model_grid.py
qcml/bench/grids/transformation_grid.py
qcml/bench/qml_benchmarking/__init__.py
qcml/bench/qml_benchmarking/hyperparameter_settings.py
qcml/data/__init__.py
qcml/data/bars_and_stripes.py
qcml/data/deepsat.py
qcml/data/eurosat.py
qcml/data/generate_bars_and_stripes.py
qcml/data/generate_hidden_manifold.py
qcml/data/generate_hyperplanes.py
qcml/data/generate_linearly_separable.py
qcml/data/generate_mnist.py
qcml/data/generate_two_curves.py
qcml/data/hidden_manifold.py
qcml/data/hyperplanes.py
qcml/data/linearly_separable.py
qcml/data/load_data.py
qcml/data/mnist.py
qcml/data/two_curves.py
qcml/kernels/__init__.py
qcml/kernels/quantum_kernels.py
qcml/kernels/classical/__init__.py
qcml/kernels/classical/anova_kernel.py
qcml/kernels/classical/chi_squared_kernel.py
qcml/kernels/classical/gaussian_kernel.py
qcml/kernels/classical/histogram_intersection_kernel.py
qcml/kernels/classical/laplacian_kernel.py
qcml/kernels/classical/linear_kernel.py
qcml/kernels/classical/polynomial_kernel.py
qcml/kernels/classical/rbf_kernel.py
qcml/kernels/classical/sigmoid_kernel.py
qcml/kernels/classical/jax/__init__.py
qcml/kernels/classical/jax/anova_kernel.py
qcml/kernels/classical/jax/chi_squared_kernel.py
qcml/kernels/classical/jax/classical_kernels.py
qcml/kernels/classical/jax/gaussian_kernel.py
qcml/kernels/classical/jax/histogram_intersection_kernel.py
qcml/kernels/classical/jax/laplacian_kernel.py
qcml/kernels/classical/jax/linear_kernel.py
qcml/kernels/classical/jax/polynomial_kernel.py
qcml/kernels/classical/jax/rbf_kernel.py
qcml/kernels/classical/jax/sigmoid_kernel.py
qcml/kernels/classical/numpy/__init__.py
qcml/kernels/classical/numpy/anova_kernel.py
qcml/kernels/classical/numpy/chi_squared_kernel.py
qcml-0.1.2.2.dist-info/LICENSE
qcml-0.1.2.2.dist-info/METADATA
qcml-0.1.2.2.dist-info/WHEEL
qcml-0.1.2.2.dist-info/top_level.txt
qcml-0.1.2.2.dist-info/RECORD
