Metadata-Version: 2.1
Name: qcml
Version: 0.1.2.2
Summary: A benchmarking library for quantum and classical machine learning, with specialized support for evaluating kernel methods.
Author-email: Albert Nieto <nietom.albert@gmail.com>
License: Apache-2.0
Project-URL: Homepage, https://github.com/albertnieto/qcml
Classifier: Programming Language :: Python :: 3
Classifier: License :: OSI Approved :: Apache Software License
Classifier: Operating System :: OS Independent
Requires-Python: >=3.6
License-File: LICENSE
